simple_keystore-0.8.0.dist-info/METADATA
simple_keystore-0.8.0.dist-info/WHEEL
simple_keystore-0.8.0.dist-info/entry_points.txt
simple_keystore-0.8.0.dist-info/licenses/LICENSE
simple_keystore/__init__.py
simple_keystore/get_available_key_for_use.py
simple_keystore/get_key_with_most_uses_remaining.py
simple_keystore/manage_simple_keys.py
simple_keystore/simple_keystore.py
simple_keystore/sks_rate_throttler.py
simple_keystore-0.8.0.dist-info/RECORD
