Metadata-Version: 2.1
Name: simple_keystore
Version: 0.8.0
Summary: "A simple encrypted key storage, now with a simple throttler (using Redis)"
Author-Email: Paul <paul@nowfree.org>
License: MIT
Project-URL: Repository, https://github.com/eyecantell/simple_keystore
Project-URL: Issues, https://github.com/eyecantell/simple_keystore/issues
Requires-Python: >=3.10
Requires-Dist: cryptography>=43.0.0
Requires-Dist: fakeredis>=2.27.0
Requires-Dist: freezegun>=1.5.1
Requires-Dist: pytest>=8.3.4
Requires-Dist: python-redis-rate-limit>=0.0.10
Requires-Dist: redis>=5.2.1
Requires-Dist: tabulate>=0.9.0
